MISSINGVALUES101703038/MissingValues.py
MISSINGVALUES101703038-1.0.0.dist-info/LICENSE.txt
MISSINGVALUES101703038-1.0.0.dist-info/METADATA
MISSINGVALUES101703038-1.0.0.dist-info/WHEEL
MISSINGVALUES101703038-1.0.0.dist-info/entry_points.txt
MISSINGVALUES101703038-1.0.0.dist-info/top_level.txt
MISSINGVALUES101703038-1.0.0.dist-info/RECORD
